{
  "sellers": [
    {
      "name": "PGE Obrót",
      "negative_prices_allowed": false,
      "tariffs": [
        { "name": "G11", "is_dynamic": false },
        { "name": "G12", "is_dynamic": false },
        { "name": "G12w", "is_dynamic": false },
        { "name": "Dynamic", "exchange_fee": 2.0, "trade_fee": 5.0, "is_dynamic": true }
      ]
    },
    {
      "name": "Tauron Sprzedaż",
      "negative_prices_allowed": false,
      "tariffs": [
        { "name": "G11", "is_dynamic": false, "energy_prices_netto_mwh": { "all": 502.03 } },
        { "name": "G12", "is_dynamic": false, "energy_prices_netto_mwh": { "high": 547.97, "low": 417.97 } },
        { "name": "G12w", "is_dynamic": false, "energy_prices_netto_mwh": { "high": 626.83, "low": 417.97 } },
        { "name": "G13", "is_dynamic": false, "energy_prices_netto_mwh": { "mid_peak": 471.79, "peak": 783.01, "off_peak": 426.02 } },
        { "name": "Dynamic", "exchange_fee": 109.7, "trade_fee": 0, "is_dynamic": true }
      ]
    },
    {
      "name": "Enea",
      "negative_prices_allowed": false,
      "tariffs": [
        { "name": "G11", "is_dynamic": false },
        { "name": "G12", "is_dynamic": false }
      ]
    },
    {
      "name": "Energa Obrót",
      "negative_prices_allowed": false,
      "tariffs": [
        { "name": "G11", "is_dynamic": false },
        { "name": "G12", "is_dynamic": false }
      ]
    },
    {
      "name": "E.ON Polska",
      "negative_prices_allowed": false,
      "tariffs": [
        { "name": "G11", "is_dynamic": false },
        { "name": "G12", "is_dynamic": false }
      ]
    },
    {
      "name": "Custom",
      "negative_prices_allowed": false,
      "tariffs": [
        { "name": "Custom", "exchange_fee": 0.0, "trade_fee": 0.0, "is_dynamic": true }
      ]
    },
    {
      "name": "Pstryk",
      "negative_prices_allowed": true,
      "tariffs": [
        { "name": "Dynamic", "exchange_fee": 80.0, "trade_fee": 0.0, "is_dynamic": true }
      ]
    }
  ],
  "distributors": [
    {
      "name": "PGE Dystrybucja",
      "tariffs": [
        {
          "name": "G11",
          "zones": {
            "all": {
              "rate": 120.0,
              "schedule": [{ "default": true }]
            }
          },
          "fixed_fees": {
            "fixed_transmission_fee": 12.3,
            "transitional_fee": 0.0,
            "subscription_fee": 5.5,
            "capacity_fee": 21.13
          }
        },
        {
          "name": "G12",
          "zones": {
            "low": {
              "rate": 90.0,
              "schedule": [
                { "hours": [22,23,0,1,2,3,4,5], "days": "all", "season": "all" },
                { "hours": [13,14], "days": "workdays", "season": "winter" },
                { "hours": [15,16], "days": "workdays", "season": "summer" }
              ]
            },
            "high": {
              "rate": 490.0,
              "schedule": [{ "default": true }]
            }
          },
          "fixed_fees": {
            "fixed_transmission_fee": 12.3,
            "transitional_fee": 0.0,
            "subscription_fee": 5.5,
            "capacity_fee": 21.13
          }
        },
        {
          "name": "G12w",
          "zones": {
            "low": {
              "rate": 90.0,
              "schedule": [
                { "hours": [22,23,0,1,2,3,4,5], "days": "all", "season": "all" },
                { "hours": [13,14], "days": "workdays", "season": "winter" },
                { "hours": [15,16], "days": "workdays", "season": "summer" },
                { "hours": [0,1,2,3,4,5,6,7,8,9,10,11,12,13,14,15,16,17,18,19,20,21,22,23], "days": "weekends", "season": "all" },
                { "hours": [0,1,2,3,4,5,6,7,8,9,10,11,12,13,14,15,16,17,18,19,20,21,22,23], "days": "holidays", "season": "all" }
              ]
            },
            "high": {
              "rate": 490.0,
              "schedule": [{ "default": true }]
            }
          },
          "fixed_fees": {
            "fixed_transmission_fee": 12.3,
            "transitional_fee": 0.0,
            "subscription_fee": 5.5,
            "capacity_fee": 21.13
          }
        }
      ]
    },
    {
      "name": "Tauron Dystrybucja",
      "tariffs": [
        {
          "name": "G11",
          "zones": {
            "all": {
              "rate": 289.92,
              "schedule": [{ "default": true }]
            }
          },
          "fixed_fees": {
            "fixed_transmission_fee": 13.4,
            "transitional_fee": 0.0,
            "subscription_fee": 5.6,
            "capacity_fee": 21.13
          }
        },
        {
          "name": "G12",
          "zones": {
            "low": {
              "rate": 99.27,
              "schedule": [
                { "hours": [22,23,0,1,2,3,4,5], "days": "all", "season": "all" },
                { "hours": [13,14], "days": "workdays", "season": "all" }
              ]
            },
            "high": {
              "rate": 327.56,
              "schedule": [{ "default": true }]
            }
          },
          "fixed_fees": {
            "fixed_transmission_fee": 13.4,
            "transitional_fee": 0.0,
            "subscription_fee": 5.6,
            "capacity_fee": 21.13
          }
        },
        {
          "name": "G12w",
          "zones": {
            "low": {
              "rate": 94.72,
              "schedule": [
                { "hours": [22,23,0,1,2,3,4,5], "days": "all", "season": "all" },
                { "hours": [13,14], "days": "workdays", "season": "all" },
                { "hours": [0,1,2,3,4,5,6,7,8,9,10,11,12,13,14,15,16,17,18,19,20,21,22,23], "days": "weekends", "season": "all" },
                { "hours": [0,1,2,3,4,5,6,7,8,9,10,11,12,13,14,15,16,17,18,19,20,21,22,23], "days": "holidays", "season": "all" }
              ]
            },
            "high": {
              "rate": 366.33,
              "schedule": [{ "default": true }]
            }
          },
          "fixed_fees": {
            "fixed_transmission_fee": 10.86,
            "transitional_fee": 0.0,
            "subscription_fee": 0.38,
            "capacity_fee": 24.05
          }
        },
        {
          "name": "G13",
          "zones": {
            "mid_peak": {
              "rate": 263.82,
              "schedule": [
                { "hours": [7,8,9,10,11,12], "days": "workdays", "season": "all" }
              ]
            },
            "peak": {
              "rate": 433.33,
              "schedule": [
                { "hours": [19,20,21], "days": "workdays", "season": "summer" },
                { "hours": [16,17,18,19,20], "days": "workdays", "season": "winter" }
              ]
            },
            "off_peak": {
              "rate": 82.70,
              "schedule": [{ "default": true }]
            }
          },
          "fixed_fees": {
            "fixed_transmission_fee": 10.86,
            "transitional_fee": 0.0,
            "subscription_fee": 4.5,
            "capacity_fee": 24.05
          }
        }
      ]
    },
    {
      "name": "Enea Operator",
      "tariffs": [
        {
          "name": "G11",
          "zones": {
            "all": {
              "rate": 120.0,
              "schedule": [{ "default": true }]
            }
          },
          "fixed_fees": {
            "fixed_transmission_fee": 5.0,
            "transitional_fee": 0.0,
            "subscription_fee": 2.0,
            "capacity_fee": 10.0
          }
        },
        {
          "name": "G12",
          "zones": {
            "low": {
              "rate": 80.0,
              "schedule": [
                { "hours": [22,23,0,1,2,3,4,5], "days": "all", "season": "all" },
                { "hours": [13,14], "days": "workdays", "season": "all" }
              ]
            },
            "high": {
              "rate": 160.0,
              "schedule": [{ "default": true }]
            }
          },
          "fixed_fees": {
            "fixed_transmission_fee": 5.0,
            "transitional_fee": 0.0,
            "subscription_fee": 2.0,
            "capacity_fee": 10.0
          }
        }
      ]
    },
    {
      "name": "Energa Operator",
      "tariffs": [
        {
          "name": "G11",
          "zones": {
            "all": {
              "rate": 120.0,
              "schedule": [{ "default": true }]
            }
          },
          "fixed_fees": {
            "fixed_transmission_fee": 5.0,
            "transitional_fee": 0.0,
            "subscription_fee": 2.0,
            "capacity_fee": 10.0
          }
        },
        {
          "name": "G12",
          "zones": {
            "low": {
              "rate": 80.0,
              "schedule": [
                { "hours": [22,23,0,1,2,3,4,5], "days": "all", "season": "all" },
                { "hours": [13,14], "days": "workdays", "season": "all" }
              ]
            },
            "high": {
              "rate": 160.0,
              "schedule": [{ "default": true }]
            }
          },
          "fixed_fees": {
            "fixed_transmission_fee": 5.0,
            "transitional_fee": 0.0,
            "subscription_fee": 2.0,
            "capacity_fee": 10.0
          }
        }
      ]
    },
    {
      "name": "Stoen Operator",
      "tariffs": [
        {
          "name": "G11",
          "zones": {
            "all": {
              "rate": 120.0,
              "schedule": [{ "default": true }]
            }
          },
          "fixed_fees": {
            "fixed_transmission_fee": 5.0,
            "transitional_fee": 0.0,
            "subscription_fee": 2.0,
            "capacity_fee": 10.0
          }
        },
        {
          "name": "G12",
          "zones": {
            "low": {
              "rate": 80.0,
              "schedule": [
                { "hours": [22,23,0,1,2,3,4,5], "days": "all", "season": "all" },
                { "hours": [13,14], "days": "workdays", "season": "all" }
              ]
            },
            "high": {
              "rate": 160.0,
              "schedule": [{ "default": true }]
            }
          },
          "fixed_fees": {
            "fixed_transmission_fee": 5.0,
            "transitional_fee": 0.0,
            "subscription_fee": 2.0,
            "capacity_fee": 10.0
          }
        }
      ]
    },
    {
      "name": "Custom",
      "tariffs": [
        {
          "name": "Custom",
          "zones": {
            "all": {
              "rate": 0.0,
              "schedule": [{ "default": true }]
            }
          },
          "fixed_fees": {
            "fixed_transmission_fee": 0.0,
            "transitional_fee": 0.0,
            "subscription_fee": 0.0,
            "capacity_fee": 0.0
          }
        }
      ]
    }
  ]
}
